ZhongLaiOlividaYi/README.md
ZhongLaiOlividaYi/__init__.py
ZhongLaiOlividaYi/__main__.py
ZhongLaiOlividaYi/file.epub
ZhongLaiOlividaYi/index.html
ZhongLaiOlividaYi/css/__init__.py
ZhongLaiOlividaYi/css/annotations.css
ZhongLaiOlividaYi/css/main.css
ZhongLaiOlividaYi/css/normalize.css
ZhongLaiOlividaYi/css/popup.css
ZhongLaiOlividaYi/font/__init__.py
ZhongLaiOlividaYi/font/fontello.eot
ZhongLaiOlividaYi/font/fontello.svg
ZhongLaiOlividaYi/font/fontello.ttf
ZhongLaiOlividaYi/font/fontello.woff
ZhongLaiOlividaYi/img/__init__.py
ZhongLaiOlividaYi/img/annotator-glyph-sprite.png
ZhongLaiOlividaYi/img/annotator-icon-sprite.png
ZhongLaiOlividaYi/img/apple-touch-icon.png
ZhongLaiOlividaYi/img/cancelfullscreen.png
ZhongLaiOlividaYi/img/close.png
ZhongLaiOlividaYi/img/fullscreen.png
ZhongLaiOlividaYi/img/loader.gif
ZhongLaiOlividaYi/img/menu-icon.png
ZhongLaiOlividaYi/img/save.png
ZhongLaiOlividaYi/img/saved.png
ZhongLaiOlividaYi/img/settings-s.png
ZhongLaiOlividaYi/img/settings.png
ZhongLaiOlividaYi/img/star.png
ZhongLaiOlividaYi/js/__init__.py
ZhongLaiOlividaYi/js/epub.js
ZhongLaiOlividaYi/js/epub.min.js
ZhongLaiOlividaYi/js/epub.min.map
ZhongLaiOlividaYi/js/hooks.min.js
ZhongLaiOlividaYi/js/hooks.min.map
ZhongLaiOlividaYi/js/reader.js
ZhongLaiOlividaYi/js/reader.js.map
ZhongLaiOlividaYi/js/reader.min.js
ZhongLaiOlividaYi/js/reader.min.map
ZhongLaiOlividaYi/js/hooks/__init__.py
ZhongLaiOlividaYi/js/hooks/extensions/__init__.py
ZhongLaiOlividaYi/js/hooks/extensions/highlight.js
ZhongLaiOlividaYi/js/libs/__init__.py
ZhongLaiOlividaYi/js/libs/jquery.min.js
ZhongLaiOlividaYi/js/libs/localforage.min.js
ZhongLaiOlividaYi/js/libs/screenfull.js
ZhongLaiOlividaYi/js/libs/screenfull.min.js
ZhongLaiOlividaYi/js/libs/zip.min.js
ZhongLaiOlividaYi/js/plugins/__init__.py
ZhongLaiOlividaYi/js/plugins/hypothesis.js
ZhongLaiOlividaYi/js/plugins/search.js
zhong_lai_olivida_yi-2024.3.3.0.dist-info/METADATA
zhong_lai_olivida_yi-2024.3.3.0.dist-info/WHEEL
zhong_lai_olivida_yi-2024.3.3.0.dist-info/entry_points.txt
zhong_lai_olivida_yi-2024.3.3.0.dist-info/top_level.txt
zhong_lai_olivida_yi-2024.3.3.0.dist-info/RECORD
